quic_version_detector
