Metadata-Version: 1.0
Name: quic-version-detector
Version: 0.1.2
Summary: Simple tool to query QUIC servers for their supported versions.
Home-page: https://github.com/povilasb/quic-version-detector
Author: Povilas Balciunas
Author-email: balciunas90@gmail.com
License: MIT
Platform: UNKNOWN
